{
    "Abstract": "Admission to MCA (Regular Course) Course, Kerala 2020-21",
    "Subsection": [
        "Higher Education",
        "Technical Education"
    ],
    "Status": "filling of vacant/lapsed seats",
    "Order Status": "Orders issued",
    "Order ID": "1364_2020_HEDN",
    "Place": "Thiruvananthapuram",
    "Date": "02/11/2020",
    "Order Issued By": "C AJAYAN ADDITIONAL SECRETARY",
    "Body": "In the circumstances reported by the Director, LBS Centre for Science and Technology, Thiruvananthapuram as per letter read as 7) paper above, Government are now pleased to order as follows fixing the criteria for filling the vacant/lapsed seats for the admission to MCA course for the academic year 2020-21: (a) Managements concerned can admit students into vacant/lapsed seats of MCA course through spot admission after the allotment by LBS Centre for Science and Technology, Thiruvananthapuram is completed. (b) After the process mentioned at (a) above is over, admission into still vacant seats can be filled from students who have not apphed through LBS Centre for Science and Technology, Thiruvananthapuram due to COVID exigencies, but has fulfilled the eligibility criteria at the tme of admission.",
    "References": [
        "606_2020_HEDN",
        "249_2020_HEDN",
        "923_2020_HEDN",
        "943_2020_HEDN",
        "1005_2020_HEDN",
        "295_2020_HEDN"
    ],
    "Department": "HIGHER EDUCATION (J) DEPARTMENT"
}